{
  "S1-1": {
    "pre_track": "null",
    "post_track": "S2-1",
    "is_allocated": false,
    "is_alive": true
  },
    "S1-2": {
    "pre_track": "null",
    "post_track": "S2-2",
    "is_allocated": false,
    "is_alive": true
  },
   "S1-3": {
    "pre_track": "null",
    "post_track": "S2-3",
    "is_allocated": false,
    "is_alive": true
  },
  "S1-4": {
    "pre_track": "null",
    "post_track": "S2-4",
    "is_allocated": false,
    "is_alive": true
  },
  "S2-1": {
    "pre_track": "S1-1",
    "post_track": "S3-1",
    "is_allocated": false,
    "is_alive": true
  }

}
